{
  "experiment_id": "exp005",
  "model_type": "Advanced_Feature_Engineering_CatBoost_Ensemble",
  "ensemble_method": "equal_weights",
  "lgb_weight": 0.3333333333333333,
  "xgb_weight": 0.3333333333333333,
  "cat_weight": 0.3333333333333333,
  "features": [
    "Episode_Length_minutes",
    "Host_Popularity_percentage",
    "Publication_Day",
    "Publication_Time",
    "Guest_Popularity_percentage",
    "Number_of_Ads",
    "Episode_Sentiment",
    "Ad_Density",
    "Host_Guest_Popularity_Diff",
    "Has_Guest",
    "Episode_Length_squared",
    "Episode_Length_log",
    "Host_Guest_Popularity_Sum",
    "Host_Guest_Popularity_Ratio",
    "Ads_per_Hour",
    "Has_Ads",
    "Length_Host_Interaction",
    "Length_Guest_Interaction",
    "Ads_Host_Interaction",
    "Ads_Guest_Interaction",
    "Sentiment_Length_Interaction",
    "Sentiment_Host_Interaction",
    "Is_Weekend",
    "Is_Weekday",
    "Hour_of_Day",
    "Is_Prime_Time",
    "Is_Morning",
    "Is_Evening",
    "Is_Late_Night",
    "Popularity_Density",
    "Ad_Effectiveness",
    "Listen_Potential",
    "Content_Quality_Score",
    "Episode_Length_minutes_Genre_Mean",
    "Host_Popularity_percentage_Genre_Mean",
    "Guest_Popularity_percentage_Genre_Mean",
    "Episode_Sentiment_Genre_Mean",
    "Episode_Length_minutes_Podcast_Mean",
    "Host_Popularity_percentage_Podcast_Mean",
    "Episode_Length_minutes_Day_Mean",
    "Host_Popularity_percentage_Day_Mean",
    "Host_Popularity_percentage_Hour_Mean",
    "Guest_Popularity_percentage_Hour_Mean",
    "Podcast_Name_encoded",
    "Episode_Title_encoded",
    "Genre_encoded",
    "Episode_Length_Category_encoded",
    "Host_Popularity_Category_encoded",
    "Guest_Popularity_Category_encoded",
    "Combined_Popularity_Category_encoded",
    "Podcast_Name_target_encoded",
    "Episode_Title_target_encoded",
    "Genre_target_encoded"
  ],
  "num_features": 53,
  "ensemble_train_rmse": 8.616160500906737,
  "ensemble_train_mae": 6.7752360790401625,
  "ensemble_train_r2": 0.8999581120197917,
  "ensemble_val_rmse": 10.203849653254606,
  "ensemble_val_mae": 7.841693439877529,
  "ensemble_val_r2": 0.8591533124670387,
  "cv_scores": [
    10.244385268961047,
    10.24459337582403,
    10.191471781695023
  ],
  "cv_rmse_mean": 10.2268168088267,
  "cv_rmse_std": 0.024992852769286127,
  "public_score": null,
  "private_score": null,
  "train_size": 431232,
  "test_size": 250000,
  "target_variable": "Listening_Time_minutes",
  "cv_folds": 3,
  "validation_split": 0.2,
  "random_state": 42,
  "preprocessing": {
    "outlier_removal": "IQR_method",
    "missing_value_strategy": "median_imputation",
    "categorical_encoding": "label_encoding_and_target_encoding",
    "feature_engineering": "advanced_20plus_features",
    "normalization": "StandardScaler"
  },
  "improvement_over_exp003": 2.5669831911733
}